[
  {
    "name": "Dưới đây là danh sách các khách sạn, resort, homestay ở khu vực Sơn Trà/Đà Nẵng:",
    "url": "https://bookingtoursontra.com/homestay-son-tra-da-nang/",
    "content": "[Bỏ qua nội dung](https://bookingtoursontra.com/homestay-son-tra-da-nang/#main)\n_Bạn có biết, khu vực Sơn Trà luôn là “thánh địa” nghỉ dưỡng lý tưởng nhất Đà Nẵng không? Nếu bạn đang tìm kiếm một chỗ ở vừa độc đáo, vừa ấm cúng, lại có bếp riêng để tự tay nấu hải sản thì[**homestay Sơn Trà Đà Nẵng**](https://bookingtoursontra.com/homestay-son-tra-da-nang/) chính là lựa chọn số một._\n_Trong bài viết này, Booking Tour Sơn Trà sẽ “mổ xẻ” 12 homestay nổi bật nhất, phân loại theo từng gu du lịch cụ thể của bạn. Đảm bảo bạn sẽ tìm được “ngôi nhà thứ hai” hoàn hảo để tận hưởng trọn vẹn kỳ nghỉ._\nNỘI DUNG\n## **1. TOP 12 homestay Sơn Trà theo từng gu du lịch**\n### **1.1. Mộc House Homestay**\n  * **Địa chỉ:** 02/06 Võ Văn Kiệt, An Hải Bắc, Sơn Trà, Đà Nẵng\n  * **Mức giá tham khảo:** Liên hệ\n\n\nMộc House không chỉ dùng gỗ làm vật liệu trang trí; nó dùng gỗ để tạo ra cảm giác “Nội tại & Cố định”—một phong cách Thiền đậm chất Á Đông. Các phòng nghỉ ở đây tránh xa sự lòe loẹt, tập trung vào ánh sáng tự nhiên và độ thoáng khí. Đây là điểm mạnh cân bằng giữa kiến trúc và môi trường, với cam kết sử dụng vật liệu thân thiện.\nThiết kế của Mộc House là sự đầu tư vào sức khỏe tinh thần, lý tưởng cho ai muốn tìm kiếm một _homestay quận Sơn Trà Đà Nẵng_ để “cắt kết nối” với thế giới ồn ào và làm việc tĩnh lặng. Hơn nữa, khu vực sân vườn nhỏ nhưng được chăm chút kỹ lưỡng, tạo ra một “khoảng đệm xanh” giúp lọc tiếng ồn từ phố xá, mang lại giấc ngủ sâu hơn.\nMộc House – Một trong các homestay Sơn Trà Đà Nẵng có không gian tĩnh\n### **1.2. Carol’s Homestay & Apartment**\n  * **Địa chỉ:** 45 An Mỹ, Sơn Trà, Đà Nẵng, Thành phố Đà Nẵng\n  * **Mức giá tham khảo:** Khoảng 300.000 VNĐ/phòng/đêm\n\n\nĐiểm mạnh nhất của Carol’s là sự chuyển đổi từ homestay truyền thống sang apartment có dịch vụ. Đây không phải là nơi để bạn giao lưu cộng đồng quá nhiều, mà là nơi bạn tìm thấy tiện nghi của một căn hộ độc lập (cửa sổ lớn ngắm bình minh, hồ bơi ngoài trời ở một số cơ sở) nhưng với mức giá mềm hơn khách sạn 4 sao.\nCarol’s là lựa chọn thông minh cho những ai đang cân nhắc thuê _homestay ở Sơn Trà Đà Nẵng_ và ưu tiên sự tự chủ. Các căn hộ Studio ở đây được trang bị bếp đầy đủ (bếp từ, lò vi sóng), rất phù hợp cho những chuyến đi dài ngày cần tự chủ trong việc ăn uống. Vị trí của Carol’s nằm gần các siêu thị mini lớn, tối ưu hóa tiện lợi cho việc tự cung tự cấp.\nCarol’s Homestay Sơn Trà Đà Nẵng trang bị đầy đủ thiết bị A-Z\n### **1.3. DUNU Homestay**\n  * **Địa chỉ:** 19 Mai Hắc Đế, An Hải Trung, Sơn Trà, Đà Nẵng\n  * **Mức giá tham khảo:** Phòng 1 – 2 người: 350.000 VNĐ/đêm, phòng 3 người: 450.000 VNĐ/đêm, phòng 4 người: 550.000 VNĐ/đêm\n\n\nDUNU nổi bật là “Thư viện sách cộng đồng khổng lồ” ở phòng sinh hoạt chung. Thiết kế tông Xanh-Trắng tạo ra một “neo cảm xúc” nhẹ nhàng, sử dụng các vật liệu thủ công như gốm sứ và vải linen để tăng tính ấm cúng.\nNếu bạn đi một mình, DUNU còn là nơi lý tưởng để tìm một góc tĩnh tại và khám phá cuốn sách yêu thích. Khu vực chung không chỉ để đọc sách mà còn được t",
    "status": 200,
    "success": true
  },
  {
    "name": "1. Wink Hotel Danang Riverside",
    "url": "https://wink-hotels.com/hotel/wink-icon-danang-riverside/",
    "content": "### Wink Live© Serviced Residences\nThank you for signing up for Wink Rewards Lifestyle.\nYou can now log in to your account\n### BOOK A ROOM\n###  Welcome to Wink Rewards Lifestyle Program \nSign-in and start enjoying exclusive discounts and perks for your stay \nFEEDBACK\nBOOK NOW \n#####  WINK HOTEL DANANG RIVERSIDE \n###  Our destination hotel & suites. \nExplore three floors of bars, restaurants and entertainment below. Or venture up to our designer Endless Summer Rooftop Bar & Lounge. On one side of Wink Hotel Danang Riverside is hip My Khe Beach with its beach bars + food trucks + sumptuous seafood restaurants. On the other side, the energy of downtown Danang where you can find Wink Hotel Danang Centre. Dive in. \n[ BOOK NOW ](https://www.hyatt.com/unscripted-by-hyatt/en-US/vn102-wink-hotel-danang-riverside)\n### Room & Suites\n1 QUEEN BED \n  * 1 QUEEN BED\n  * 20 SQM\n  * NEIGHBORHOOD VIEW\n  * 2 ADULTS + 1 CHILD\n\n\nOur Queen Bedrooms are space-smart and chic sanctuaries in Danang's vibrant centre – smart design meets coastal city energy for solo travelers and couples exploring Danang's beach and urban buzz. \n1 QUEEN BED CITY VIEW \n  * 1 QUEEN BED\n  * 20 SQM\n  * CITY VIEW\n  * 2 ADULTS + 1 CHILD\n\n\nOur space-smart and chic Queen Bed City View rooms serve up sensational views over Danang – compact sanctuaries where solo travelers and couples recharge between exploring Danang's waterfront and beaches. \n2 TWIN BEDS CITY VIEW \n  * 2 TWIN BEDS\n  * 20 SQM\n  * CITY VIEW\n  * 2 ADULTS \n\n\nBirds of a feather stay together in our space-smart and chic Twin Bed City View rooms – two single beds overlooking Danang where travel buddies' recharge between exploring Danang's waterfront and beaches. \n1 QUEEN BED RIVER VIEW \n  * 1 QUEEN BED\n  * 20 SQM\n  * RIVER VIEW\n  * 2 ADULTS + 1 CHILD\n\n\nOur space-smart and chic Queen Bed River View rooms serve up sensational views over the Han River – compact sanctuaries where solo travelers and couples watch the riverside life unfold while exploring Danang's waterfront and beaches. \n2 TWIN BEDS RIVER VIEW \n  * 2 TWIN BEDS\n  * 20 SQM\n  * RIVER VIEW\n  * 2 ADULTS\n\n\nBirds of a feather stay together in our space-smart and chic Twin Bed River View rooms – two single beds overlooking the Han River where travel buddies' recharge between exploring Danang's waterfront and beaches. \n2 TWIN BEDS CITY VIEW DELUXE \n  * 2 TWIN + 1 BUNK BED\n  * 30 SQM\n  * CITY VIEW\n  * 3 ADULTS / 2 ADULTS + 1 CHILD\n\n\nOur Twin Bed City View Deluxe rooms pack two single beds and one bunk with sweeping city views – where families and friends recharge between exploring Danang's waterfront and beaches. \n1 KING BED CITY VIEW DELUXE \n  * 1 KING + 1 BUNK BED\n  * 30 SQM\n  * CITY VIEW\n  * 3 ADULTS + 1 CHILD\n\n\nOur King Bed City View Deluxe rooms pack one king and one bunk with sweeping city views – where families and friends recharge between exploring Danang's waterfront and beaches. \n2 TWIN BEDS RIVER VIEW DELUXE \n  * 2 TWIN + 1 BUNK BED\n  * 30 SQM\n  * RIVER VIEW\n  * 3 ADULTS / 2 A",
    "status": 200,
    "success": true
  },
  {
    "name": "2. Novotel Đà Nẵng",
    "url": "https://www.klook.com/vi/blog/novotel-da-nang/",
    "content": "klook.com\n",
    "status": 403,
    "success": false
  },
  {
    "name": "3. Sontra Sea Hotel",
    "url": "https://sontraseahotel.com/",
    "content": "[Skip to content](https://sontraseahotel.com/#main)\n# SONTRA SEA HOTEL – ĐIỂM HẸN BÊN BIỂN ĐÀ NẴNG\nNằm trên con đường Hoàng Sa thơ mộng, **Sontra Sea Hotel** là một trong những **khách sạn mặt biển Đà Nẵng** được yêu thích. Với tầm nhìn hướng biển tuyệt đẹp và không gian yên bình, khách sạn mang đến trải nghiệm nghỉ dưỡng hoàn hảo.\nVị trí đắc địa giúp du khách dễ dàng khám phá các điểm nổi tiếng như Cầu Rồng, bãi biển Mỹ Khê, và bán đảo Sơn Trà. Sontra Sea Hotel là lựa chọn lý tưởng để tận hưởng kỳ nghỉ thoải mái và bắt đầu hành trình khám phá Đà Nẵng.\n_– Khách sạn chỉ sử dụng DUY NHẤT các thông tin chính thức sau để liên hệ và nhận thanh toán: Hotline/Zalo: 0936 790 798 – Số tài khoản: 1040186843 – Ngân hàng: Vietcombank – Tên tài khoản: CT TNHH KHACH SAN SSH_\n_– Ngoài các thông tin nêu trên, khách sạn không sử dụng bất kỳ số điện thoại hoặc tài khoản nào khác. Để đảm bảo an toàn, Quý khách vui lòng xác minh trực tiếp qua số hotline chính thức trước khi thực hiện thanh toán._\n## TIN TỨC NỔI BẬT \n##### [CHÚC MỪNG NGÀY QUỐC TẾ THIẾU NHI 1/6 – MÙA HÈ CỦA NHỮNG TIẾNG CƯỜI & KỲ NGHỈ GIA ĐÌNH ĐÁNG NHỚ 01/06/2026 Mỗi mùa hè đi qua đều để lại những ký ức rất riêng trong tuổi thơ của [...] XEM CHI TIẾT  ](https://sontraseahotel.com/quoc-te-thieu-nhi-1-6-mua-he-gia-dinh-sontra-sea-hotel/)\n##### [ĐI BIỂN CÙNG GIA ĐÌNH – Ở ĐÂU ĐỂ VỪA TIỆN, VỪA THOẢI MÁI? 26/05/2025 Gợi ý khách sạn gia đình gần biển Đà Nẵng cho kỳ nghỉ mùa hè đáng nhớ [...] XEM CHI TIẾT  ](https://sontraseahotel.com/di-bien-cung-gia-dinh-da-nang/)\n##### [MÙA PHÁO HOA ĐÀ NẴNG 2026 ĐÃ BẮT ĐẦU – TẬN HƯỞNG KỲ NGHỈ BIỂN TRỌN VẸN TẠI SONTRA SEA HOTEL Đà Nẵng mùa hè 2026 – thành phố biển sôi động nhất miền Trung Mỗi khi mùa hè [...] XEM CHI TIẾT  ](https://sontraseahotel.com/khach-san-mat-bien-son-tra-mua-phao-hoa-2026/)\n##### [CHÚC MỪNG ĐẠI LỄ 30/4 – 1/5 Không khí biển Sơn Trà những ngày này thật rộn ràng – nắng đẹp, gió mát và từng [...] XEM CHI TIẾT  ](https://sontraseahotel.com/30-04-01-05/)\n##### [30/4 TẠI SONTRA SEA HOTEL – BIỂN XANH, NẮNG ĐẸP VÀ MỘT KỲ NGHỈ TRỌN VẸN 06/04/2026 1. Khách sạn mặt biển Sơn Trà – nơi kỳ nghỉ thực sự bắt đầu Kỳ nghỉ [...] XEM CHI TIẾT  ](https://sontraseahotel.com/khach-san-mat-bien-son-tra-30-4/)\n##### [KHÔNG LO HẾT PHÒNG ĐẸP – SONTRA SEA HOTEL ĐA DẠNG HẠNG PHÒNG, THOẢI MÁI LỰA CHỌN! Bạn đang lên kế hoạch cho chuyến hành trình khám phá thành phố biển Đà Nẵng xinh đẹp? [...] XEM CHI TIẾT  ](https://sontraseahotel.com/sontra-sea-hotel-da-nang-2/)\n##### [SONTRA SEA HOTEL – KHÁCH SẠN VEN BIỂN SƠN TRÀ: ĐIỂM DỪNG CHÂN LÝ TƯỞNG TẠI ĐÀ NẴNG Bạn đang tìm kiếm một không gian nghỉ dưỡng yên bình, nơi có thể lắng nghe tiếng sóng [...] XEM CHI TIẾT  ](https://sontraseahotel.com/sontra-sea-hotel-da-nang/)\n##### [TẾT ĐÃ QUA – THỜI ĐIỂM ĐẸP NHẤT ĐỂ NGHỈ DƯỠNG ĐẦU NĂM Ở ĐÀ NẴNG Khi không khí Tết vừa lắng lại, đây chính là lúc Đà Nẵng trở về nhịp bình [...] XEM CHI TIẾT  ](https://sontraseahotel.com/khach-san-mat-bien-son-tra-thoi-diem-nghi-duong/)\n##### [PHÒNG ĐẸP – VIEW XỊN – GI",
    "status": 200,
    "success": true
  },
  {
    "name": "4. Ania Beachside Hotel",
    "url": "https://vn.trip.com/hotels/da-nang-hotel-detail-131763586/ania-beachside-hotel-da-nang/",
    "content": "  * Xe\n  * [Tour & Hoạt Động](https://vn.trip.com/things-to-do/?locale=vi-VN&curr=VND \"Tour & Hoạt Động\")\n  * Cảm Hứng Du Lịch\n\n\nỨng Dụng\nĐăng Cơ Sở Lưu Trú\nChăm sóc khách hàng\nTìm Đặt Chỗ\nAnia Beachside Hotel Da Nang\nChọn ngày\n-\nChọn ngày\n1 đêm\n1 phòng, 2 Người Lớn, 0 Trẻ Em\nTất Cả Các Khách Sạn Ở Đà Nẵng\nAnia Beachside Hotel Da Nang\n# Ania Beachside Hotel Da Nang\nKhai trương năm 2025\n42 Hà Kỳ Ngộ, Sơn Trà, Đà Nẵng, Việt Nam, Sơn Trà, Đà Nẵng\nXem trên bản đồ\nChúng Tôi Khớp Giá\nChọn Phòng\nĐược đặt lần gần nhất 8 giờ trước\nĐiểm Nổi Bật\nDịch vụ xuất sắc\nRất sạch sẽ\nNhà nghỉ dưỡng bên bờ biển\nVị trí lý tưởng\nBãi biển\n+3 mục khác\nTiện nghi\nWi-Fi ở khu vực chung\nCamera giám sát ở khu vực chung\nTất Cả Tiện Nghi\nMô tả cơ sở lưu trú\nAnia Beachside Hotel Đà Nẵng ở Sơn Trà, Đà Nẵng, cách Bãi biển Mỹ Khê và Sông Hàn5 phút lái xe. Khách sạn bãi biển này cách Chợ Hàn 4 km và cách Nhà thờ Đà Nẵng 4,3 km.\nXem Thêm\n_9,1_ _/10_\nTuyệt Vời\nPhòng thoáng , sạch sẽ , c chủ và c lễ Tân thân thiện, thoải mái dễ thương ạaa\nTất Cả 119 Đánh Giá\nXem xung quanh đây\nKhu thương mại: Bãi biển Mỹ Khê\n(2,8km)\nĐiểm tham quan: Công viên Tượng đài Mân Thái\n(520m)\nVui chơi giải trí: The Backpacker Hostel & Spa (Da Nang)\n(400m)\nĐiểm tham quan: Công viên cá voi\n(700m)\nĐiểm tham quan: Garden by the Beach Mural\n(800m)\nXem Trên Bản Đồ\n## Phòng\n## Đánh Giá Của Khách\n## Tiện nghi & Dịch vụ\n## Chính Sách\nChọn Phòng\n### Phòng Deluxe Gia đình với Tầm nhìn ra Biển\n2 Giường queen\n30m² | Tầng: 4\nCó cửa sổ\nWi-Fi miễn phí\nKhông hút thuốc\nPhòng Tắm Riêng\nTủ lạnh\nBar mini\nThông Tin Phòng\nKiểm Tra Phòng Trống\n### Phòng Deluxe với Cửa sổ(giường queen)\n1 Giường queen\n30m² | Tầng: 1-3\nCó cửa sổ\nWi-Fi miễn phí\nKhông hút thuốc\nPhòng Tắm Riêng\nTủ lạnh\nBar mini\nThông Tin Phòng\nKiểm Tra Phòng Trống\n### Phòng Superior với Cửa sổ(giường queen)\n1 Giường queen\n30m² | Tầng: 1-5\nCó cửa sổ\nWi-Fi miễn phí\nKhông hút thuốc\nPhòng Tắm Riêng\nTủ lạnh\nBar mini\nThông Tin Phòng\nKiểm Tra Phòng Trống\n### Phòng Tiêu chuẩn có Cửa sổ(giường đôi)\n1 Giường đôi\n30m² | Tầng: 1-4\nCó cửa sổ\nWi-Fi miễn phí\nKhông hút thuốc\nPhòng Tắm Riêng\nTủ lạnh\nBar mini\nThông Tin Phòng\nKiểm Tra Phòng Trống\nXem 1 Loại Phòng Còn Lại\n## Đánh Giá Của Khách\n/10\nTuyệt Vời\n119 đánh giá\nĐánh Giá Xác Thực\n  * Vệ sinh\n  * Trang thiết bị\n  * Vị trí\n  * Dịch vụ\n\n\nTrung bình các cơ sở lưu trú tương tự tại Đà Nẵng\nCác đánh giá thường nhắc đến\nTất cả đánh giá (119)Đánh giá tích cực (115)Đánh giá có ảnh/video (25)Dịch vụ tuyệt vời (50)Phòng tuyệt vời (38)Thời gian lưu trú tuyệt vời! (25)Rất đáng giá tiền (20)Bãi biển tuyệt vời (15)Gần biển (15)Vị trí thuận tiện (14)Yên tĩnh & thoải mái (12)Đánh giá tiêu cực (4)\nKhách nói gì\nT‍à‍i‍ ‍k‍h‍o‍ả‍n‍ ‍k‍h‍á‍c‍h\nngày 5 tháng 3 năm 2026\nCăn phòng rất thoải mái. Đó là đêm tuyệt vời nhất trong chuyến đi này. Dịch vụ lễ tân rất thân thiện và hữu ích với tôi rất nhiều. Lễ tân cũng có thể giao tiếp bằng tiếng Anh. Nó rất trôi chảy. Đó là một trải nghiệm tốt. Hẹn gặp lại lần sau.\nT‍à‍i‍ ‍k‍h‍o‍ả‍n‍ ‍k‍h‍á‍c‍h\nngày 23 tháng 12 năm 202",
    "status": 200,
    "success": true
  },
  {
    "name": "5. Le Sands Oceanfront Danang Hotel",
    "url": "https://lesandshotel.com/",
    "content": "## Where Indulgence Begins\nLocated in beautiful coastal of Da Nang and overlooking the incredible beach, Le Sands Oceanfront Da Nang Hotel with 106 elegant Rooms & Residence is your launching pad into boundless adventures, where you can soak up the sun and enjoy full-filled activities throughout your holiday.\n#### [Save More, Enjoy More! Check our Special Offers ›](https://lesandshotel.com/special-offers/)\n## Le Sands Oceanfront Danang Hotel\nProud to be one of the best top-rated hotels in Da Nang, Le Sands is contemporary in design with state-of-the-art facilities definitely will be an appropriate location for couples, group of friends or spacious enough for families...who looking for the best place to stay in Da Nang for a marvelous beach holiday.\n[About Us](https://lesandshotel.com/the-hotel/)\n#### [Rooms & Residences](https://lesandshotel.com/rooms-residences/)\n#### [Restaurant](https://lesandshotel.com/reviera-restaurant/)\n#### [Rooftop Bar](https://lesandshotel.com/bs-sky-bar/)\n#### [Wellness Spa](https://lesandshotel.com/azure-spa/)\n#### [Infinity Pool](https://lesandshotel.com/rooftop-infinity-pool/)\n#### [Meeting & Event](https://lesandshotel.com/meeting-event/)\n## Le Sands Oceanfront Danang Hotel\nProud to be one of the best top-rated hotels in Da Nang, Le Sands is contemporary in design with state-of-the-art facilities definitely will be an appropriate location for couples, group of friends or spacious enough for families...who looking for the best place to stay in Da Nang for a marvelous beach holiday.\n[About Us](https://lesandshotel.com/the-hotel/)\n## Explore our Rooms & Residences\nWe deliver uncompromising convenience for a refined travel, complete leisure and business experience.\n## Explore our Rooms & Residences\nWe deliver uncompromising convenience for a refined travel, complete leisure and business experience.\n### [Deluxe Ocean The most popular Rooms for all Purposes An ultimate relaxation, featured by generous comforts and fully-equipped amenities, awaits you in one of our spacious Deluxe Ocean Room. ](https://lesandshotel.com/rooms-suites/deluxe-ocean/)\n### [Premier Deluxe Ocean Features for Corporate A striking collaboration between modern design and subtle luxury in an instantly inviting space. ](https://lesandshotel.com/rooms-suites/premier-oceanfront/)\n### [1 Bedroom Residence Oceanfront A tribute to taste and elegance Sense the feeling of home in your own 1-bedroom residence oceanfront with a spacious living room. ](https://lesandshotel.com/rooms-suites/1-bedroom-residence-oceanfront/)\n### [2 Bedroom Residence Oceanfront The Best choice for Group Our guest-favorite apartments of 102sqm features 02 bedrooms, a spacious living room, direct the ocean view. ](https://lesandshotel.com/rooms-suites/2-bedroom-residence-oceanfront/)\n### [3 Bedroom Residence Oceanfront The luxury of abundant space This is an elegant recidence for families or large group of friends to spend their time together. ](https://lesandshotel.com/rooms-suites",
    "status": 200,
    "success": true
  },
  {
    "name": "6. Palmier Hotel Da Nang",
    "url": "https://palmierhoteldanang.vn-hotels.com/en/",
    "content": "  1. [ VietNam  ](https://www.vn-hotels.com/en/)\n  2. [ Da Nang ](https://www.vn-hotels.com/en/destination/vietnam-da-nang-municipality-da-nang)\n  3. [ Palmier Hotel - Art House Da Nang ](https://palmierhoteldanang.vn-hotels.com/en/)\n  4. Information and booking website - unofficial \n\n\n#  [ Palmier Hotel - Art House Da Nang ](https://palmierhoteldanang.vn-hotels.com)\n  * |\n  *   * [ Language ](javascript:;)\n    * [ English ](https://palmierhoteldanang.vn-hotels.com/en/ \"English\")\n    * [ Español ](https://palmierhoteldanang.vn-hotels.com/es/ \"Español\")\n    * [ Français ](https://palmierhoteldanang.vn-hotels.com/fr/ \"Français\")\n    * [ Italiano ](https://palmierhoteldanang.vn-hotels.com/it/ \"Italiano\")\n    * [ Português ](https://palmierhoteldanang.vn-hotels.com/pt/ \"Português\")\n    * [ Deutsch ](https://palmierhoteldanang.vn-hotels.com/de/ \"Deutsch\")\n    * [ Filipino ](https://palmierhoteldanang.vn-hotels.com/tl/ \"Filipino\")\n    * [ Bahasa Malaysia ](https://palmierhoteldanang.vn-hotels.com/ms/ \"Bahasa Malaysia\")\n    * [ Tiếng Việt ](https://palmierhoteldanang.vn-hotels.com/vi/ \"Tiếng Việt\")\n    * [ ภาษาไทย ](https://palmierhoteldanang.vn-hotels.com/th/ \"ภาษาไทย\")\n    * [ हिन्दी ](https://palmierhoteldanang.vn-hotels.com/in/ \"हिन्दी\")\n\n\nOnline booking Best price guaranteed | FROM 155.743,80 (VND) SEARCH AVAILABILITY \n### How can we help you?\n**Leave us your email and an agent will offer you the best option according to your search**\n#### Best Price Guaranteed\nClose \nBook on our site!\n**Up to 10% less** than on Booking.com\n**Free cancellation!**\n##  Palmier Hotel - Art House Da Nang | Vietnam - Da Nang \n305 Tran Hung Dao, An Hai Bac, Son Tra, Da Nang, Vietnam [ (Show map) ](javascript:)\n###  Palmier Hotel - Art House Da Nang description \nSituated in Da Nang, 1.9 km from My Khe Beach, Palmier Hotel Da Nang features accommodation with a restaurant, free private parking, a bar and a garden. Boasting family rooms, this property also provides guests with a terrace. The accommodation offers a 24-hour front desk, airport transfers, room service and free WiFi throughout the property.\nAt the hotel, rooms are equipped with a wardrobe. All rooms at Palmier Hotel Da Nang have air conditioning and a desk.\nThe accommodation offers a buffet or à la carte breakfast.\nPopular points of interest near Palmier Hotel Da Nang include Song Han Bridge, Love Lock Bridge Da Nang and Indochina Riverside Mall. The nearest airport is Da Nang International Airport, 6 km from the hotel.\n######  See photos for Palmier Hotel - Art House Da Nang \nSee more \n####  Palmier Hotel - Art House Da Nang \n  * [ **Details** ](https://palmierhoteldanang.vn-hotels.com/en/)\n  * [ **Rooms** ](https://palmierhoteldanang.vn-hotels.com/en/#componentRooms)\n  * [ **Services** ](https://palmierhoteldanang.vn-hotels.com/en/#componentServices)\n  * [ **Conditions** ](https://palmierhoteldanang.vn-hotels.com/en/#componentConditions)\n  * [ **Reviews** ](https://palmierhoteldanang.vn-hotels.com/en/#reviewCo",
    "status": 200,
    "success": true
  },
  {
    "name": "7. Peninsula Hotel Danang",
    "url": "https://peninsulahotel.vn/",
    "content": "#### PENINSULA HOTEL DANANG\nWhether you're here to unwind, explore, or celebrate, every moment is thoughtfully crafted to become a lasting memory.\n#### PENINSULA HOTEL DANANG\nLuxury nestled by the tranquil My Khe beach\n#### PENINSULA HOTEL DANANG\n#### HALAL ROYALE LOUNGE\nExperience exquisite Halal dining with a panoramic city view Level 28 - Peninsula Hotel Danang\n#### PENINSULA HOTEL DANANG\nWhether you're here to unwind, explore, or celebrate, every moment is thoughtfully crafted to become a lasting memory.\n#### PENINSULA HOTEL DANANG\nLuxury nestled by the tranquil My Khe beach\n#### PENINSULA HOTEL DANANG\n#### HALAL ROYALE LOUNGE\nExperience exquisite Halal dining with a panoramic city view Level 28 - Peninsula Hotel Danang\n## EXPERIENCING THE PERFECT LIFE AT THE PENINSULA HOTEL DA NANG\nPeninsula Hotel Danang located at 84 Vo Nguyen Giap Street, Son Tra District, Danang City. The Peninsula Hotel Danang has 259 rooms which have a view of the sea, city, and Son Tra Peninsula. The hotel has a restaurant, a lounge, an infinity pool, a gym, a bar, and a ballroom to make your holiday complete.The Peninsula Hotel Danang offers a blend of the best Eastern and Western hospitality in an atmosphere of unmatched classical grandeur and timeless elegance.\n[More info](https://peninsulahotel.vn/experiences \"EXPERIENCING THE PERFECT LIFE AT THE PENINSULA HOTEL DA NANG\")\n## Type Room\n[View All](https://peninsulahotel.vn/accommodation \"View All\")\n### [Grand Executive Ocean Queen](https://peninsulahotel.vn/grand-executive-ocean-queen \"Grand Executive Ocean Queen\")\nRelax and listen to the waves whisper in your ears, experience the infinity pool, and enjoy a romantic dinner under the starry sky. If you are looking for a private retreat, leaving behind the hustle and bustle of the city, Grand Executive Ocean Queen is the best choice for you.The room rate is inclusive of afternoon tea. \n### [Elizabeth Suite](https://peninsulahotel.vn/elizabeth-suite \"Elizabeth Suite\")\nImmerse yourself in the vast expanse of Son Tra peninsula and marvel at the immense beauty of the sea and distant woodland peaks. Elizabeth Suite, with its 85 square meters, balcony, and classic European-style bathroom, is a great choice for a relaxing stay with family and friends.The room rate is inclusive of afternoon tea. \n### [Peninsula Suite](https://peninsulahotel.vn/peninsula-suite \"Peninsula Suite\")\nLocated on the 23rd floor of the hotel with a direct view of the sea, an area of 130 square meters, including 1 queen bed & 2 twin beds. Peninsula Suite is the perfect choice for a relaxing stay with family and friends. The room rate is inclusive of afternoon tea. \n### [Deluxe City View Queen](https://peninsulahotel.vn/deluxe-city-queen \"Deluxe City View Queen\")\nFrom the 5th to the 26th floor, a vibrant and bustling city scene of Da Nang can be seen. Deluxe City Queen has a highly classic yet modern style, making it ideal for business trips or travel. A desk, free internet access, and many other ameniti",
    "status": 200,
    "success": true
  },
  {
    "name": "8. Son Tra Resort & Spa",
    "url": "https://sontraresort.com.vn/",
    "content": "# Experience Tranquility at Son Tra Resort & Spa\nExperience luxury on the beautiful beachfront.\n### About Son Tra Resort\n**Experience luxury and tranquility at our beachfront paradise.**\nNestled in a private bay on the stunning **Son Tra Peninsula** , **Son Tra Resort & Spa** is an exclusive beachfront retreat just 15 minutes from **Da Nang city center** and 20 minutes from **Da Nang International Airport**.Embraced by lush mountains and overlooking the crystal-clear sea, the resort offers a perfect harmony of nature and elegance — a peaceful escape from the noise and bustle of everyday life.\nLocated beside beaches once voted by **Forbes** as among the **six most beautiful in the world** , Son Tra Resort is surrounded by the untouched forest known as the **“green lung” of Vietnam** , home to rare flora and fauna species.Each private villa features a spacious design, an outdoor swimming pool, and breathtaking ocean views — creating the ultimate sanctuary for relaxation and privacy.\nWhether you seek a romantic getaway, a family retreat, or a serene escape into nature, **Son Tra Resort & Spa** invites you to indulge in refined comfort and unforgettable memories.Once you visit, you’ll surely want to return.\n**Recreation & Facilities**• Restaurant & Bar• Swimming Pool• Spa & Massage• Beach Volleyball• Water Sports Activities• SUP & Kayaking\n### Gallery\n_[Explore the beauty of Son Tra Resort& Spa](https://sontraresort.com.vn/villas)_\nAbsolutely thrilled with my purchase! Outstanding product, exceptional service, and overall an excellent buying experience.\nClarice Turner\nAbsolutely thrilled with my purchase! Outstanding product, exceptional service, and overall an excellent buying experience.\nBrian Moten\n###### ★★★★★\n###### ★★★★★\n##### SON TRA RESORT & SPA\nSon Tra Joint Stock CompanyTax Code: **0400451173** Issued on **August 4, 2003** by **Da Nang Department of Finance – Business Registration Office.**\n**Contact**\n**Inquiry**\nEmail: info@sontraresort.com\nPhone: +84 236 3 924 924 Hotline: +84 345 924 925\n© 2025. Son Tra Resort & Spa. Official Site\nAdd: Bai Nam - Bai Con, Son Tra Ditrict, Da Nang City, Viet Nam \n### _[Privacy Policy](https://sontraresort.com.vn/privacy-policy)_\n### _[Business rules](https://sontraresort.com.vn/business-rules)_\n",
    "status": 200,
    "success": true
  },
  {
    "name": "9. Golden Sea Hotel",
    "url": "https://duonggiahotel.vn/da-nang-o-mien-nao/",
    "content": "11 Th3\nĐà Nẵng được đánh giá là thành phố năng động nhất Việt Nam với tốc độ phát triển kinh tế – xã hội đáng tự hào trong những năm qua. Chính vì thế, [**du lịch Đà Nẵng**](https://dulichsontra.com/kinh-nghiem-du-lich-da-nang) luôn thu hút được nhiều du khách đến tham quan và nghỉ dưỡng. Vậy **Đà Nẵng ở miền nào**? Đà Nẵng có điều gì hấp dẫn du khách như thế? Những câu hỏi này sẽ được giải đáp ngay dưới bài viết này nhé.\n## Đà Nẵng ở miền nào?\nĐà Nẵng là một trong 5 thành phố trực thuộc Trung ương bao gồm: Thủ đô Hà Nội, Tp.Hồ Chí Minh, Tp. Hải Phòng, Tp. Cần Thơ và Tp. Đà Nẵng. Đà Nẵng cũng là thành phố trực thuộc duy nhất nằm ở khu vực miền Trung – Tây Nguyên.\nĐà Nẵng ở miền nào? Thời điểm lý tưởng để du lịch Đà Nẵng\nTham khảo Tour du lịch Đà Nẵng 2024 hấp dẫn từ Công ty du lịch Khát Vọng Việt tại <https://dulichkhatvongviet.com/du-lich-trong-nuoc/du-lich-da-nang/>\nĐà Nẵng là trung tâm kinh tế, đồng thời cũng là một trong những trung tâm văn hóa, giáo dục, khoa học và công nghệ lớn của đất nước. Nếu bạn muốn biết [**Đà Nẵng ở miền nào**](https://duonggiahotel.vn/da-nang-o-mien-nao/) nữa thì thành phố này thuộc vùng duyên hải Nam Trung Bộ, rộng hơn là thuộc miền Trung – Tây Nguyên. Nơi đây cũng sở hữu nhiều địa điểm du lịch nổi tiếng trong nước và quốc tế. Mỗi năm, Đà thành luôn thu hút hàng triệu lượt khách trong và ngoài nước đến tham quan, nghỉ dưỡng.\n### Nên ở khách sạn nào ở Đà Nẵng\n**[Dương Gia Hotel](https://duonggiahotel.vn/)** luôn là lựa chọn hàng đầu của du khách khi đến Đà Nẵng nhờ vị trí thuận lợi, gần biển Mỹ Khê và giá cả hợp lý. Khách sạn đạt tiêu chuẩn 3.5 sao, nội thất đẹp sang trọng hiện đại và không gian thoải mái đem lại trải nghiệm lưu trú chất lượng cho khách hàng.\nDương Gia Hotel là khách sạn chuẩn 3.5 sao dịch vụ tốt, phòng đẹp sang trọng\nGiá phòng tại Dương Gia Hotel đang ưu đãi, giảm đến 70% cho khách hàng.\n  * Phòng 1 giường lớn 2 khách giá 200.000đ/1 đêm\n  * Phòng 2 giường lớn 4 khách giá 400.000đ/1 đêm\n\n\n> Đặt phòng, bạn liên hệ hotline **[0983.72.82.86](tel:0983728286)** để nhận đúng giá ưu đãi như trên.\n## Lịch sử hình thành Đà Nẵng\nTrước kia thì trên bản đồ Việt Nam vẫn chưa xuất hiện vùng đất nào tên Đà Nẵng. Vào năm 1306 vua Chiêm Thành – tên gọi của tiểu vương quốc Chăm Pa xưa là Chế Mân và vua Trần Nhân Tông – vua của nước Đại Việt có thỏa ước dâng 2 vùng đất là Châu Ô tức Thuận Châu (bắc Hải Vân) và Châu Rí tức Hóa Châu (nam Hải Vân) dùng làm sính lễ để cưới Huyền Trân công chúa – con gái của vua Trần Nhân Tông. Dần dần người Việt đến sinh sống tại 2 vùng đất này, người dân Chiêm Thành lui dần về phía nam của vương quốc.\nĐà Nẵng – thành phố năng động sáng tạo và đáng sống nhất Việt Nam\nXuôi theo dòng lịch sử, mảnh đất Quảng Nam đã từng là nơi đóng đô của vương quốc triều đại cổ suốt 15 thế kỉ. Năm 1471, Quảng Nam trở thành 1 bộ phận quan trọng của nước Đại Việt dưới thời vua Trần Nhân Tông. Vào thời điểm chúa Trịnh – Nguyễn phân tranh thì vùng đất này thuộc quyền cai quản của chúa Nguyễn ở đàng trong bắt đầ",
    "status": 200,
    "success": true
  },
  {
    "name": "10. InterContinental Danang Sun Peninsula",
    "url": "https://www.danang.intercontinental.com/",
    "content": "[Skip to content](https://www.danang.intercontinental.com/#content)\n# A high-style seaside retreat wrapped in pristine rainforest\n##  A high-style seaside retreat wrapped in pristine rainforest\n## Recharge your imagination in our private, perfect world\nCelebrate sunshine and seclusion at one of Vietnam’s most spectacular beach resorts. Retreat into a world of unspoiled nature, set on our private bay, where you’ll be enlivened by bold, creative architecture that marries local heritage with world-class design. From top-tier destination dining to barefoot days of beachside bliss, savour every moment as our team crafts the perfect experience, grounded in Vietnamese hospitality.\n## Photo Gallery\n[ Explore ](https://www.danang.intercontinental.com/gallery/)\nRoom & Suites\nVilla Collection\nRoom & Suites\nDiscover delight and inspiration in our guestrooms, alive with thoughtful touches and open to fresh air and nature. Surround yourself with true comfort and in-the-know hospitality.\nVilla Collection\nDiscover delight and inspiration in our luxurious guestrooms and suites, alive with thoughtful touches and open to fresh air and nature. Surround yourself with true comfort and in-the-know hospitality.\n## Room & Suites\nDiscover delight and inspiration in our guestrooms, alive with thoughtful touches and open to fresh air and nature. Surround yourself with true comfort and in-the-know hospitality.\n## Villa Collection\nDiscover delight and inspiration in our luxurious guestrooms and suites, alive with thoughtful touches and open to fresh air and nature. Surround yourself with true comfort and in-the-know hospitality.\n## Unforgettable Experiences\n### Once-in-a-lifetime moments\n#### Say Yes! Package\nSay Yes! at Vietnam’s most iconic resort \n[ Read More ](https://www.danang.intercontinental.com/offers/say-yes-wedding-proposal-offer/)\n#### Michelin Star Dining\nIndulge in the magic of La Maison 1888 by Christian Le Squer \n[ Read More ](https://www.danang.intercontinental.com/dining/la-maison-1888/)\n#### A Modern Japanese Dining Adventure\nTeppanyaki, Omakase & Sushi by Michelin Chef Junichi Yoshida \n[ Read More ](https://www.danang.intercontinental.com/dining/tingara/)\n#### It’s Time for a Daycation!\nEnjoy a entire day with complete access to our recreation facilities, and more! \n[ Read More ](https://www.danang.intercontinental.com/experiences/daycation/)\n#### Digital Design Walking Tour\nExplore the inspiration behind our architect, Bill Bensley, with this design walking tour. \n[ Read More ](https://www.danang.intercontinental.com/bensley-digital-design-tour/)\n#### VIP Kids Explorer Experience\nWhat kid doesn’t love camping? Make your family’s visit unforgettable with our VIP Kids Explorer Experience. \n[ Read More ](https://www.danang.intercontinental.com/offers/vip-kids-package/)\n#### Explore our Spectacular Nature\nMeet our nature experts and (perhaps) a rare douc langur \n[ Read More ](https://www.danang.intercontinental.com/amenities/wildlife-conservation/)\n#### The I",
    "status": 200,
    "success": true
  },
  {
    "name": "11. The Code Hotel",
    "url": "https://rosamiahotel.com/",
    "content": "\n",
    "status": 200,
    "success": false
  },
  {
    "name": "12. The Backpacker Hostel",
    "url": "http://www.brendonkearns.com/2014/04/21/da-nang-hoi-an-and-nha-trang/",
    "content": "# Site Not Found\nWell, this is awkward. The site you're looking for is not here.\nIs this your site? [Get more info](https://help.dreamhost.com/hc/en-us/articles/215613517) or [contact support](https://panel.dreamhost.com/index.cgi?tree=support.dashboard).\n[DreamHost](https://www.dreamhost.com/)\n",
    "status": 307,
    "success": true
  },
  {
    "name": "13. Nguyen Gia Hotel",
    "url": "https://huongtinhvytravel.com/nguyen-gia-hotel/",
    "content": "None",
    "status": null,
    "success": false
  },
  {
    "name": "14. Hà Nội Hotel",
    "url": "https://en.planetofhotels.com/vietnam/da-nang/ha-noi-hotel-4731561",
    "content": "# en.planetofhotels.com\n## Performing security verification\nThis website uses a security service to protect against malicious bots. This page is displayed while the website verifies you are not a bot.\n## Verification successful. Waiting for en.planetofhotels.com to respond\nRay ID: `a08957e9ad72106e`\nPerformance and Security by [Cloudflare](https://www.cloudflare.com?utm_source=challenge&utm_campaign=m)[Privacy](https://www.cloudflare.com/privacypolicy/)\n",
    "status": 307,
    "success": true
  },
  {
    "name": "15. Mangata Beachfront Hotel",
    "url": "https://mangatahotel.vn/vi",
    "content": "## [VỀ MANGATA](https://mangatahotel.vn/about-mangata \"VỀ MANGATA\")\nMangata Beachfont là khách sạn nghỉ dưỡng 4 sao cao cấp tọa lạc trên cung đường Võ Nguyên Giáp với bờ biển trải dài đầy thơ mộng. Từ Khách sạn Quý khách chỉ mất 1 phút đi bộ ra biển, cách trung tâm thành phố 4,5 km, cách sân bay Đà Nẵng 6,6 km, cách các danh lam thắng cảnh như Bà Nà Hills...\n[Xem chi tiết](https://mangatahotel.vn/about-mangata \"VỀ MANGATA\")\nprev\nnext\n\n\n04\n## [SUITE DOUBLE](https://mangatahotel.vn/phong \"SUITE DOUBLE\")\nPhòng được trang bị đầy đủ tiện nghi hiện đại, nội thất thanh lịch, phòng tắm với bồn tắm nằm tạo cảm giác thư giãn sảng khoái.\n[Xem chi tiết](https://mangatahotel.vn/phong \"SUITE DOUBLE\")\n05\n## [EXECUTIVE DOUBLE/TWIN](https://mangatahotel.vn/phong \"EXECUTIVE DOUBLE/TWIN\")\nNội thất gỗ thanh lịch, phòng được trang bị đầy đủ tiện nghi hiện đại, phòng tắm với khu vực tắm đứng, tạo sự thoải mái.\n[Xem chi tiết](https://mangatahotel.vn/phong \"EXECUTIVE DOUBLE/TWIN\")\n06\n## [PREMIER TRIPLE](https://mangatahotel.vn/phong \"PREMIER TRIPLE\")\nNội thất gỗ thanh lịch, phòng được trang bị đầy đủ tiện nghi hiện đại, phòng tắm với khu vực tắm đứng, tạo sự thoải mái.\n[Xem chi tiết](https://mangatahotel.vn/phong \"PREMIER TRIPLE\")\n07\n## [PREMIER DOUBLE/ TWIN](https://mangatahotel.vn/phong \"PREMIER DOUBLE/ TWIN\")\nNội thất gỗ thanh lịch, phòng được trang bị đầy đủ tiện nghi hiện đại, phòng tắm với khu vực tắm đứng rộng rãi.\n[Xem chi tiết](https://mangatahotel.vn/phong \"PREMIER DOUBLE/ TWIN\")\n01\n## [DELUXE TWIN / DOUBLE](https://mangatahotel.vn/phong \"DELUXE TWIN / DOUBLE\")\nNội thất gỗ thanh lịch, phòng được trang bị đầy đủ tiện nghi, phòng tắm với khu vực tắm đứng rộng rãi.\n[Xem chi tiết](https://mangatahotel.vn/phong \"DELUXE TWIN / DOUBLE\")\n02\n## [MANGATA SUITE DOUBLE](https://mangatahotel.vn/phong \"MANGATA SUITE DOUBLE\")\nPhòng bao gồm 01 phòng khách rộng rãi, 01 phòng ngủ lớn nhìn trực diện biển và bán đảo Sơn Trà được trang bị đầy đủ thiết bị hiện đại và một phòng bếp nhỏ. Phòng tắm với bồn tắm nằm tạo cảm giác thư giãn sảng khoái.\n[Xem chi tiết](https://mangatahotel.vn/phong \"MANGATA SUITE DOUBLE\")\n03\n## [SUITE FAMILY](https://mangatahotel.vn/phong \"SUITE FAMILY\")\nPhòng được trang bị đầy đủ tiện nghi hiện đại, nội thất thanh lịch. Phòng tắm với khu vực tắm đứng, tạo sự thoải mái.\n[Xem chi tiết](https://mangatahotel.vn/phong \"SUITE FAMILY\")\n04\n## [SUITE DOUBLE](https://mangatahotel.vn/phong \"SUITE DOUBLE\")\nPhòng được trang bị đầy đủ tiện nghi hiện đại, nội thất thanh lịch, phòng tắm với bồn tắm nằm tạo cảm giác thư giãn sảng khoái.\n[Xem chi tiết](https://mangatahotel.vn/phong \"SUITE DOUBLE\")\n05\n## [EXECUTIVE DOUBLE/TWIN](https://mangatahotel.vn/phong \"EXECUTIVE DOUBLE/TWIN\")\nNội thất gỗ thanh lịch, phòng được trang bị đầy đủ tiện nghi hiện đại, phòng tắm với khu vực tắm đứng, tạo sự thoải mái.\n[Xem chi tiết](https://mangatahotel.vn/phong \"EXECUTIVE DOUBLE/TWIN\")\n06\n## [PREMIER TRIPLE](https://mangatahotel.vn/phong \"PREMIER TRIPLE\")\nNội thất gỗ thanh lịch, phòng được tr",
    "status": 200,
    "success": true
  },
  {
    "name": "16. OYO 853 Son Tra Motel",
    "url": "https://www.kayak.com/Da-Nang-Hotels-Son-Tra-Hostel.3086372.ksp",
    "content": "# OYO 853 Son Tra Motel  \n2 stars\n[ 12 Ha Bong, Phuoc My, Son Tra District, Da Nang, Vietnam Da Nang, Vietnam](https://www.kayak.com/Da-Nang-Hotels-Son-Tra-Hostel.3086372.ksp)[+84 284 458 1611](https://www.kayak.com/Da-Nang-Hotels-Son-Tra-Hostel.3086372.ksp)\nFair\nbased on 26 reviews\n[26 reviews](https://www.kayak.com/Da-Nang-Hotels-Son-Tra-Hostel.3086372.ksp)\nMon 6/15\n-\nTue 6/16\n2 guests, 1 room\nSearch\nProvider\nProvider for OYO 853 Son Tra Motel\nShow Prices\nProvider for OYO 853 Son Tra Motel\nShow Prices\nProvider for OYO 853 Son Tra Motel\nShow Prices\nPhotos of OYO 853 Son Tra Motel\nOverview\nPrices\nAmenities\nReviews\nLocation\nTips & FAQs\nNearby stays\n## Latest deals for OYO 853 Son Tra Motel\nMon 6/15\n-\nTue 6/16\n2 guests, 1 room\n## Amenities at OYO 853 Son Tra Motel\n  * Free Wi-Fi\n\n\nBasics\n  * Free Wi-Fi\n\n\nShow 1 amenity\n## Reviews of OYO 853 Son Tra Motel\n5.2\nFair\n26 verified ratings\nWonderful\n5\nVery good\n1\nGood\n5\nOkay\n0\nFair\n3\nMediocre\n2\nPoor\n10\nReviews(0)\nQ&A(5)\nTips(10)\nSort by:Most recent\n### Filters\nAll filters\n### Filters\nReview rating\nTraveler type\nTime of year\n### Score by provider\n5.2/10\n5.2 out of 10\n4 reviews\nAI-powered summary based on hotel reviews by KAYAK users. AI can make mistakes.\nHow comfortable are the beds at OYO 853 Son Tra Motel?\nGuests often praise the comfortable beds at OYO 853 Son Tra Motel, ensuring a good night's sleep during your stay.\nIs parking available at OYO 853 Son Tra Motel?\nOYO 853 Son Tra Motel offers parking facilities, providing convenience for guests traveling by car.\nWhat can I expect from the food quality at OYO 853 Son Tra Motel?\nGuests have enjoyed the food quality at OYO 853 Son Tra Motel, offering satisfying dining experiences during their stay.\nHow is the cleanliness at OYO 853 Son Tra Motel?\nThe cleanliness at OYO 853 Son Tra Motel is often highlighted by guests, ensuring a pleasant and hygienic environment throughout the property.\nWhat is the level of customer service like at OYO 853 Son Tra Motel?\nGuests have appreciated the level of customer service at OYO 853 Son Tra Motel, providing attentive and friendly assistance throughout their stay.\nAI-powered summary based on hotel reviews by KAYAK users. AI can make mistakes.\nOpt for a Room Away from Street Noise\nSome guests mentioned that rooms facing the street can be noisy, so consider requesting a room away from the street for a quieter stay.\nExplore Nearby Attractions\nThe hotel is conveniently located near My Khe Beach, Han River Bridge, Da Nang Cathedral, and other attractions, making it a great base for sightseeing.\nCheck Pet Policy\nIf traveling with pets, it's advisable to check the hotel's pet policy in advance, as there may be charges and specific rules to adhere to.\nConsider Parking Availability\nThe hotel offers parking, which can be convenient for guests with a car. However, it's recommended to inquire about parking availability and any associated fees.\nVerify Wi-Fi Quality\nWhile the hotel offers free Wi-Fi, some guests mentioned issues with ",
    "status": 200,
    "success": true
  },
  {
    "name": "17. Dolphin Hotel and Apartment",
    "url": "https://dolphin-hotel-and-apartment-1.wheree.com/",
    "content": "Sorry! The page you’re looking for doesn’t exist or has been moved.\nPossible reasons:\n  * The address URL was entered incorrectly.\n  * The page has been deleted or moved.\n\n\nTry these steps:\n  * Check the URL again.\n  * Use search to find what you’re looking for.\n  * Return to our homepage <https://www.wheree.com>.\n\n\nIf the problem persists, contact us at support@wheree.com.\nSorry for the inconvenience!\nhttps://www.wheree.com\n",
    "status": 404,
    "success": true
  },
  {
    "name": "18. Grand Gold Hotel",
    "url": "https://grandgolddanang.vn-hotel.com/",
    "content": "Da Nang Municipality \nHotels \nGrand Gold Hotel Da Nang\n# Grand Gold Hotel Da Nang\n[ Lot 1 - A2.2, Hoang Sa Street, Tho Quang Ward, Son Tra District, Da Nang, Vietnam ](https://grandgolddanang.vn-hotel.com/en/#location) ex. Grand Gold Hotel & Spa\nTraveller Rating\nVery Good \n272 reviews\n8.2\n100 photos \n100 photos \n[ View on map ](https://grandgolddanang.vn-hotel.com/en/#location)\n##  Grand Gold Hotel 4* \n### Main amenities\n  * Free Wi-Fi\n  * Free parking\n  * 24-hour services\n  * Express check-in/ -out\n  * Swimming Pool\n  * Private beach\n  * Fitness/Gym\n  * Sports activities\n  * Spa and relaxation\n  * On-site Dining\n  * Meeting facilities\n  * Child-friendly\n  * Air conditioning\n  * No pets allowed\n\nShow all 14 amenities + Show less -\n### Location\nShow more + Show less -\nOffering guests a banquet hall and event rooms, suited for shared moments, the luxury Grand Gold Hotel Da Nang conveniently sits approximately 3 km from the Linh Ung Pagoda. Located in the Tho Quang Beach district of Da Nang, the 4-star hotel offers an outdoor swimming pool, a steam room, a sauna, and locker rooms.\nSituated around 10 minutes' drive from the Gothic-style pink church \"Danang Cathedral\", the hotel also gives access to such sports venues as the multi - purpose Chi Lang Stadium, which is around 15 minutes' drive away. Natural attractions in the area include the love East Sea Park, 2.5 km from the Grand Gold Da Nang, and a beach is a mere 50 metres away. Guests might as well enjoy proximity to Son Tra Ocean View Pool & Spa, situated merely an 11-minute walk away. Along with other cultural attractions the Da Nang Museum is nestled 3.6 km from the property. Bai tam Man Thai bus stop is a short way from the Grand Gold.\nThis Da Nang hotel offers rooms with a dressing area and a seating area complete with air conditioning. They are furnished with sound-proofed windows, and also come with a minibar fridge and a kettle. An alarm clock, along with a walk-in closet are featured in bedrooms. Bathrooms are equipped with a bidet, a separate toilet, and a sink, as well as comforts such as complimentary toiletries and dressing gowns. Guests can enjoy views of the mountain from Grand Gold Hotel.\nHere a continental breakfast is offered each morning. You can visit Orchid restaurant for breakfast and eat American dishes. It offers a variety of fruit desserts that will suit all tastes. The Grand Gold Da Nang invites guests to have a drink at a lounge bar.\nMore Less\n## Amenities\n#### Internet\n  * Free Wi-Fi in public areas \n\n\n#### Parking options\n  * Parking \n\n\n#### Shuttle\n  * Paid airport shuttle \n\n\n#### Activities\n  * Fitness centre \n  * Diving \n  * Snorkelling \n  * Cycling \n  * Fishing \n\n\n#### Property services\n  * Safe deposit box \n  * 24-hour reception \n  * VIP check-in/ -out \n  * Express check-in/ -out \n  * 24-hour security \n  * Luggage storage \n  * Locker room \n  * Currency exchange \n  * Room service \n  * Housekeeping \n  * Car hire \n  * Laundry \n  * Dry cleaning \n  * Tours/Ticket assi",
    "status": 200,
    "success": true
  },
  {
    "name": "19. Sujet Beach Hotel Da",
    "url": "https://danangaztravel.com/san-pham/khach-san-alisia-beach-hotel-da-nang/",
    "content": "[Bỏ qua nội dung](https://danangaztravel.com/san-pham/khach-san-alisia-beach-hotel-da-nang/#main)\n[ Chat Zalo](https://zalo.me/0876143343)\n[ Chat Messenger](https://m.me/61570531640008/)\n#  Khách sạn Alisia Beach Hotel Đà Nẵng\nVị trí đắc địa \nBán chạy nhất \n(1002 đánh giá) 1736+ đã đặt \n[ 19 Hoàng Sa, Sơn Trà ](javascript:void\\(0\\))\n🔸 Miễn phí buffet sáng 🔸 Miễn phí 02 chai nước suối, trà, cafe 🔸 Miễn phí sử dụng hồ bơi 🔸 Miễn phí sử dụng Wifi – Internet\nThông tin tại website chỉ hỗ trợ Quý du khách tham khảo thông tin dịch vụ và giá vé. Để được tư vấn chi tiết và đặt booking, Quý du khách vui lòng liên hệ **Đà Nẵng AZ Travel** qua **Messenger** hoặc **Zalo** để được hỗ trợ nhanh nhất. Trân trọng cảm ơn!\n  * [ THÔNG TIN CHI TIẾT ](https://danangaztravel.com/san-pham/khach-san-alisia-beach-hotel-da-nang/#tab-description)\n\n\nĐÀ NẴNG AZ TRAVEL\nPhone: [0876 143 343](tel:0876143343)\nZalo: [Đà Nẵng AZ Travel](https://zalo.me/0876143343)\nWhatsApp: [Đà Nẵng AZ Travel](https://wa.me/84876143343)\nFacebook: [Đà Nẵng AZ Travel](https://facebook.com/61570531640008/)\nE-mail: hi@danangaztravel.com\nWebsite: [www.danangaztravel.com](https://danangaztravel.com/)\n5/5 - (2 lượt đánh giá) \n## Default Title\n### Khách sạn Alisia Beach Hotel Đà Nẵng\n🔸 Miễn phí buffet sáng 🔸 Miễn phí 02 chai nước suối, trà, cafe 🔸 Miễn phí sử dụng hồ bơi 🔸 Miễn phí sử dụng Wifi – Internet\n(Đặt hàng nhanh và chờ nhân viên gọi điện xác nhận sau 5 phút!)\n[devvn_quickbuy] \n  * [Kinh nghiệm du lịch](https://danangaztravel.com/kinh-nghiem-du-lich/)\n  * [Liên hệ chúng tôi](https://danangaztravel.com/lien-he-da-nang-az-travel/)\n\n\n### Đăng nhập\n### Đăng ký\n",
    "status": 200,
    "success": true
  },
  {
    "name": "20. Duke Casa Apartment",
    "url": "https://apt-duke-casa.dananghotels.net/",
    "content": "This domain is registered at [**Dynadot.com**](https://www.dynadot.com). Website coming soon.\n",
    "status": 200,
    "success": false
  },
  {
    "name": "21. Lotus",
    "url": "https://www.lotuscars.com/",
    "content": "ELETREDiscover Lotus[ LOTUS CENTRES](https://www.lotuscars.com/en-VN/lotus-centres/search)\nBACK\n[LOTUS STORY](https://www.lotuscars.com/en-VN/lotus-story)[HERITAGE ROAD CARS](https://www.lotuscars.com/en-VN/lotus-story/road-cars)[HERITAGE RACE CARS](https://www.lotuscars.com/en-VN/lotus-story/race-cars)[Theory 1 concept car](https://www.lotuscars.com/en-VN/lotus-story/theory-1)[MANUFACTURING](https://www.lotuscars.com/en-VN/lotus-story/factory)[CONTACT US](https://www.lotuscars.com/en-VN/contact-us)[PRESS](https://www.lotuscars.com/en/press)\nLOCATION:\nVietnam\nVideo Player is loading.\nPlay Video\nPlay\nUnmute\nCurrent Time 0:00\nDuration -:-\nLoaded: 0%\nStream Type LIVE\nSeek to live, currently behind liveLIVE\nRemaining Time -0:00\n1x\nPlayback Rate\nChapters\n  * Chapters\n\n\nDescriptions\n  * descriptions off, selected\n\n\nSubtitles\n  * subtitles settings, opens subtitles settings dialog\n  * subtitles off, selected\n\n\nAudio Track\nPicture-in-PictureFullscreen\nThis is a modal window.\nBeginning of dialog window. Escape will cancel and close the window.\nText ColorWhite Black Red Green Blue Yellow Magenta CyanTransparencyOpaque Semi-Transparent Background ColorBlack White Red Green Blue Yellow Magenta CyanTransparencyOpaque Semi-Transparent Transparent Window ColorBlack White Red Green Blue Yellow Magenta CyanTransparencyTransparent Semi-Transparent Opaque\nFont Size 50% 75% 100% 125% 150% 175% 200% 300% 400% Text Edge Style None Raised Depressed Uniform Dropshadow Font Family Proportional Sans-Serif Monospace Sans-Serif Proportional Serif Monospace Serif Casual Script Small Caps\nReset restore all settings to the default valuesDone\nClose Modal Dialog\nEnd of dialog window.\nPURE PERFORMANCE PEDIGREE SINCE 1948\nThe unique driving experience a Lotus offers has inspired passionate drivers for more than seventy five years.\nOUR MODELS\nSetting new standards in automotive excellence on and off the track.\nLOTUS ELETRE\nThe electric hyper-SUV with racecar DNA.\nLOTUS EMIRA\nThe most powerful four-cylinder Lotus car ever made.\nLOTUS EMEYA\nThe new benchmark in hyper-GT performance.\nLOTUS EVIJA\nThe most powerful hypercar ever to enter production. Production is limited to just 130 examples.\nMODELS\nABOUT LOTUS\n[Investor relations](http://www.group-lotus.com/)\n[Terms and Conditions](https://www.lotuscars.com/en-VN/terms-conditions)[Privacy Notice](https://www.lotuscars.com/en-VN/privacy)[Cookie Statement](https://www.lotuscars.com/en-VN/cookie-statement)[Whistleblowing Centre](https://report.whistleb.com/lotus)\nVietnam\n* Lotus Cars reserves the right to revise prices in the future due to, but not limited to availability of materials, delivery costs, inflation and changes in (local) taxes. The final price of the vehicle depends on the chosen model, options, specifications and taxes. The images used on this page are of a vehicle used for promotional purposes only. The images are therefore indicative and no rights can be derived from them. The images show optional equipment. \n",
    "status": 301,
    "success": true
  },
  {
    "name": "22. Four Points by Sheraton",
    "url": "https://en.itravelblog.net/four-points-by-sheraton-danang/",
    "content": "[ Skip to main content](https://en.itravelblog.net/four-points-by-sheraton-danang/#content)\n# Four Points by Sheraton Danang: A Star-Rated Hotel with Stunning Views of the Han River and My Khe Beach\n| \nDiscover more\nUrban Transit\nHotels & Accommodations\nMaps\n[Advertisement/Sponsored Content]\n2019-06-18\npublish\n|\n2025-09-04\nrevision\nOn my last night in Da Nang, I stayed at the Four Points by Sheraton Danang. Although it didn’t have the advantage of a private beach, the room was large and had a great view. After having enough fun at the beach in the previous few days, the staff at the counter enthusiastically introduced me to it. Next, head to the city to explore Da Nang’s local snacks and markets, and enjoy affordable seafood along the beach on the return trip. (🔎Reservation prices and accommodation reviews:[agoda](https://www.agoda.com/partners/partnersearch.aspx?pcs=1&cid=1947574&hid=4974064)|[booking.com](https://www.booking.com/hotel/vn/four-points-by-sheraton-danang.zh-tw.html?aid=809084)|[Trip](https://hk.trip.com/hotels/da-nang-hotel-detail-22153383/four-points-by-sheraton-danang/?Allianceid=3249321&SID=9267577&trip_sub1=&trip_sub3=D4956905)|[klook](https://www.klook.com/zh-TW/hotels/detail/441609-four-points-by-sheraton-danang/?aid=29))\nHighlights\nHighlights\n## Basic introduction to Four Points by Sheraton Danang\n##### Reservation:[agoda](https://www.agoda.com/partners/partnersearch.aspx?pcs=1&cid=1947574&hid=4974064)|[booking.com](https://www.booking.com/hotel/vn/four-points-by-sheraton-danang.zh-tw.html?aid=809084)|[Trip](https://hk.trip.com/hotels/da-nang-hotel-detail-22153383/four-points-by-sheraton-danang/?Allianceid=3249321&SID=9267577&trip_sub1=&trip_sub3=D4956905)|[klook](https://www.klook.com/zh-TW/hotels/detail/441609-four-points-by-sheraton-danang/?aid=29)\nThe Four Points by Sheraton hotel brand was established in 1995 and is a subsidiary of Sheraton Hotels and Resorts. It is positioned as a smaller sub-brand of hotels. In 1998, Starwood Hotel Group acquired Sheraton, 2016 In the year Marriott Hotel Group acquired Starwood, Four Points Sheraton eventually became a member of the world's largest hotel group.\nFour Points by Sheraton Danang opened in 2017. It adopts a mid-priced brand positioning. It is located in the central area of ​​My Khe Beach. Although it does not have the advantage of being close to the beach, the hotel is located at a bend in the road. The view can overlook the stretch of coastline, the hotel and the same building form an apartment-style hotel─[Altara Suites by Ri-Yaz](https://www.agoda.com/partners/partnersearch.aspx?pcs=1&cid=1947574&hid=2662781), Suitable for long-term business trips and families with parents and children.\n> Related Post: [Danang Accommodation 2026｜10 Newly Opened Resorts, Star Hotels, Serviced Apartments, Budget Hotels and Hostels](https://en.itravelblog.net/new-hotels-in-da-nang/)\n▲ The counter service staff at Four Points by Sheraton Danang are very enthusiastic and will actively recom",
    "status": 200,
    "success": true
  },
  {
    "name": "Lưu ý: Tôi đã loại bỏ các thông tin không liên quan và sửa lỗi OCR. Nếu có bất kỳ lỗi nào, vui lòng cho tôi biết.",
    "url": "https://www.ilovepdf.com/vi",
    "content": "# Tất cả các công cụ bạn cần để làm việc với tệp PDF ở cùng một nơi\n## Tất cả các công cụ mà bạn cần để sử dụng PDF, đều nằm trong tầm tay bạn. Tất cả đều 100% MIỄN PHÍ và dễ dùng! Nối, tách, nén, chuyển đổi, xoay, mở khóa và thêm dấu bản quyền cho PDF chỉ với một vài lần nhấp.\nTất cả\nQuy trình làm việc\nSắp xếp PDF\nTối ưu hóa PDF\nChuyển đổi PDF\nChỉnh sửa PDF\nBảo mật PDF\nPDF thông minh\n### [Nối PDF Kết hợp PDF theo thứ tự bạn muốn với trình nối PDF dễ dùng nhất hiện có. ](https://www.ilovepdf.com/vi/ghep-pdf \"Nối PDF\")\n### [Tách PDF Tách riêng một trang hoặc nhiều trang để dễ dàng chuyển đổi sang các tệp PDF độc lập. ](https://www.ilovepdf.com/vi/cat-pdf \"Tách PDF\")\n### [Nén PDF Giảm kích thước tệp nhưng vẫn tối ưu để tệp PDF có chất lượng tối đa. ](https://www.ilovepdf.com/vi/giam-dung-l%C6%B0%E1%BB%A3ng-pdf \"Nén PDF\")\n### [PDF sang Word Dễ dàng chuyển đổi tệp PDF của bạn thành các tài liệu DOC và DOCX dễ chỉnh sửa. Tài liệu WORD đã chuyển đổi chính xác đến gần 100%. ](https://www.ilovepdf.com/vi/pdf-sang-word \"PDF sang Word\")\n### [PDF sang PowerPoint Chuyển tệp PDF của bạn thành tệp trình chiếu PPT và PPTX dễ chỉnh sửa. ](https://www.ilovepdf.com/vi/pdf-sang-powerpoint \"PDF sang PowerPoint\")\n### [PDF sang Excel Chuyển dữ liệu từ PDF thẳng sang bảng tính Excel chỉ trong giây lát. ](https://www.ilovepdf.com/vi/pdf-sang-excel \"PDF sang Excel\")\n### [Word sang PDF Làm cho tệp DOC và DOCX trở nên dễ đọc bằng cách chuyển đổi sang PDF. ](https://www.ilovepdf.com/vi/word-sang-pdf \"Word sang PDF\")\n### [PowerPoint sang PDF Làm cho tệp trình chiếu PPT và PPTX trở nên dễ đọc bằng cách chuyển đổi chúng sang PDF. ](https://www.ilovepdf.com/vi/powerpoint-sang-pdf \"PowerPoint sang PDF\")\n### [Excel sang PDF Làm cho bảng tính EXCEL trở nên dễ đọc bằng cách chuyển đổi sang PDF. ](https://www.ilovepdf.com/vi/excel-sang-pdf \"Excel sang PDF\")\n### [Chỉnh sửa PDF Thêm văn bản, hình ảnh, hình vẽ hoặc chú thích bằng tay vào tài liệu PDF. Chỉnh sửa kích cỡ, phông chữ và màu sắc của nội dung được thêm. ](https://www.ilovepdf.com/vi/trinh-chinh-sua-pdf \"Chỉnh sửa PDF\")\n### [PDF sang JPG Chuyển đổi mỗi trang PDF sang JPG hoặc xuất tất cả ảnh có trong một tệp PDF. ](https://www.ilovepdf.com/vi/pdf-sang-jpg \"PDF sang JPG\")\n### [JPG sang PDF Chuyển đổi ảnh JPG sang PDF trong giây lát. Điều chỉnh hướng và lề một cách dễ dàng. ](https://www.ilovepdf.com/vi/jpg-sang-pdf \"JPG sang PDF\")\n### [Ký tên PDF Tự ký hoặc yêu cầu chữ ký điện tử của người khác. ](https://www.ilovepdf.com/vi/them-chu-ky-va \"Ký tên PDF\")\n### [Dấu bản quyền Đóng dấu dạng ảnh hoặc văn bản lên tệp PDF của bạn chỉ trong giây lát. Chọn kiểu chữ, độ trong suốt và vị trí. ](https://www.ilovepdf.com/vi/hinh-mo-pdf \"Dấu bản quyền\")\n### [Xoay PDF Xoay PDF theo hướng bạn muốn. Bạn thậm chí có thể xoay nhiều tệp PDF cùng lúc! ](https://www.ilovepdf.com/vi/xoay-pdf \"Xoay PDF\")\n### [HTML sang PDF Chuyển đổi các trang web HTML sang PDF. Sao chép và dán URL của trang bạn muốn và chuyển đổi sang PDF với một cú nhấp chuột. ](htt",
    "status": 200,
    "success": true
  }
]